{
  "strategy_id": "FILING_SHOCK_CONTINUATION",
  "source_provenance": "D:\\Global_Ai\\Risk_Manager_Platform_Workspace\\30_ui_phase1\\output\\research\\final_platform_delivery_v1",
  "research_commit": "LEGACY_SOURCE_COMMIT_NOT_RECORDED",
  "sample_start": "2018-01-02",
  "sample_end": "2026-06-08",
  "observations": 2119,
  "cumulative_gross_return": 0.532249324638489,
  "cumulative_net_return": 0.5164785500424451,
  "gross_cumulative_return": 0.532249324638489,
  "net_cumulative_return": 0.5164785500424451,
  "annualized_return": 0.0507654309762788,
  "net_sharpe": 0.7282321338329901,
  "annualized_net_volatility": 0.0715122348238295,
  "max_drawdown": -0.172521394487667,
  "average_daily_turnover": 0.0097644686601741,
  "transaction_cost_sum": 0.0103454545454545,
  "cost_drag_ratio": 0.019437233767241085,
  "win_rate": 0.5134497404436055,
  "gross_return_mean": 0.00021153900957184528,
  "net_return_mean": 0.00020665677524175818,
  "preliminary_oos_net_return": 0.3891817698900923,
  "preliminary_oos_sharpe": 1.6318860239419055,
  "double_cost_net_return": 0.5008652223720977,
  "delayed_execution_net_return": 0.4685024891793568,
  "maximum_active_correlation": 0.7800375682633643,
  "marginal_combined_portfolio_sharpe": 0.0655453657715642,
  "decision": "KEEP_CANDIDATE",
  "research_status": "CURRENT_LISTED_DIAGNOSTIC | SURVIVORSHIP_BIAS_PRESENT | RESEARCH_CANDIDATE",
  "labels": "CURRENT_LISTED_DIAGNOSTIC | SURVIVORSHIP_BIAS_PRESENT | RESEARCH ONLY",
  "raw_summary_row": {
    "strategy_id": "FILING_SHOCK_CONTINUATION",
    "test_period_start": "2018-01-02",
    "test_period_end": "2026-06-08",
    "observations": 2119.0,
    "gross_cumulative_return": 0.532249324638489,
    "net_cumulative_return": 0.5164785500424451,
    "annualized_net_return": 0.0507654309762788,
    "net_sharpe": 0.7282321338329901,
    "annualized_volatility": 0.0715122348238295,
    "max_drawdown": -0.172521394487667,
    "average_daily_turnover": 0.0097644686601741,
    "annualized_turnover": 2.460646102363893,
    "total_cost_drag": 0.0103454545454545,
    "preliminary_oos_start": "2023-11-22",
    "preliminary_oos_convention": "Chronological 70/30 split; PRELIMINARY_OOS",
    "preliminary_oos_net_return": 0.3891817698900923,
    "preliminary_oos_sharpe": 1.6318860239419055,
    "average_eligible_count": 56.60943396226415,
    "recommendation": "KEEP_CANDIDATE",
    "research_status": "CURRENT_LISTED_DIAGNOSTIC | SURVIVORSHIP_BIAS_PRESENT | RESEARCH_CANDIDATE",
    "live_allocation_approved": false,
    "trade_cost_reconciliation_error": 0.0,
    "double_cost_net_return": 0.5008652223720977,
    "double_cost_sharpe": 0.7109338520982768,
    "delayed_execution_net_return": 0.4685024891793568,
    "delayed_execution_sharpe": 0.6751496447278182,
    "latest_max_abs_weight": 0.0454545454545454,
    "latest_weight_hhi": 0.0454545454545454,
    "actual_universe_used": "US_BROAD_LIQUID_POINT_IN_TIME_DIAGNOSTIC_FALLBACK",
    "maximum_active_correlation": 0.7800375682633643,
    "average_active_correlation": 0.2560214495759146,
    "highest_active_correlation_strategy": "FUNDAMENTAL_MOMENTUM",
    "marginal_combined_portfolio_sharpe": 0.0655453657715642,
    "economic_rationale": "Continuation after point-in-time filing improvement.",
    "labels": "CURRENT_LISTED_DIAGNOSTIC | SURVIVORSHIP_BIAS_PRESENT | RESEARCH ONLY",
    "execution_enabled": false,
    "classification": "ACTIVE",
    "classification_reason": "Positive standalone, OOS, robustness, and marginal portfolio evidence.",
    "regime_strength": "MARKET_PROXY_GROWTH_DOWN_INFLATION_UP",
    "regime_weakness": "MARKET_PROXY_GROWTH_DOWN_INFLATION_DOWN"
  }
}
